{
  "action": "create",
  "approval_mode": "approve",
  "approved_by": "owner",
  "artifact_id": "DCL-DISPATCHER-DAEMON-RECOVERY-SLA-001",
  "artifact_type": "design_constraint",
  "change_reason": "WI-4884 owner-approved daemon-resilience DCL recording per DELIB-20266354",
  "changed_by": "gt-cli",
  "explicit_change_request": "AUQ DELIB-20266354: Owner approved the exact six daemon-resilience formal artifacts for WI-4884 and authorized Prime Builder to record them in MemBase.",
  "full_content": "## Constraint\n\nThe dispatcher daemon must provide automatic recovery behavior for the failure\nmodes selected in `DELIB-20266276`, with bounded recovery expectations that are\nmeasurable by tests or operational probes.\n\n## Applicability\n\nThis constraint applies to daemon liveness monitoring, worker lifecycle\nmanagement, state checkpointing, harness saturation handling, provider\ncircuit-breaking, and dispatch retry logic.\n\n## Required Recovery SLAs\n\n| Failure mode | Required recovery behavior | Recovery expectation |\n| --- | --- | --- |\n| Daemon death | Scheduled supervisor restarts through ensure-alive. | Restart within roughly one supervisor interval plus startup time. |\n| Worker hang | Daemon kills the worker at the configured lifetime cap and re-dispatches eligible work when safe. | Recovery begins immediately after lifetime-cap expiry. |\n| Worker crash | Daemon reaps the crashed worker, records the failure, and re-dispatches eligible work when safe. | Recovery begins on the next daemon lifecycle sweep. |\n| Spawn storm | Watchdog or daemon recovery reaps runaway workers and suppresses further unsafe spawning. | Recovery begins within one watchdog or daemon recovery cycle. |\n| Corrupt daemon state | Daemon resets to the latest known-good checkpoint or safe empty state with audit evidence. | Recovery begins on detection; no silent use of corrupt state. |\n| Harness saturation | Daemon backs off and does not exceed the per-harness one-worker cap. | Backoff applies immediately when saturation is detected. |\n| Provider outage | Daemon circuit-breaks or suppresses the failing provider/harness and reroutes to eligible healthy alternatives. | Reroute begins after failure threshold is met. |\n\nThe system must not require owner action for ordinary recovery within these\nmodes.\n\n## Rationale\n\nThe owner selected full auto-recovery for all listed modes. Recovery SLAs turn\nthat decision into testable constraints so later implementation phases cannot\nclaim resilience merely because a daemon process exists.\n\n## Required Behavior\n\n1. Each failure mode must have explicit detection and recovery logic.\n2. Each recovery decision must leave enough audit evidence to diagnose what\n   happened.\n3. Recovery must respect the daemon single-instance invariant and the harness\n   isolation invariant.\n4. Recovery must not silently abandon bridge work. Work is either completed,\n   re-dispatched, parked with evidence, or escalated visibly.\n5. Recovery tests must prefer deterministic STUB workers for load and chaos\n   cases, with real harness smoke checks only.\n\n## Verification Expectations\n\n- Deterministic STUB tests cover hang, crash, corrupt output or state, and load\n  saturation without spending real provider calls.\n- Real harness smoke tests prove the recovery pathway still composes actual\n  harness commands at least once per harness class.\n- Status or health commands expose enough state to tell healthy, degraded, and\n  blocked recovery apart.\n\n## Source Decisions\n\n- `DELIB-20266276` D1: fleet-saturation load target.\n- `DELIB-20266276` D2: full auto-recovery, all modes.\n- `DELIB-20266276` D5: STUB load and chaos; real smoke only.\n\n",
  "full_content_sha256": "91f372fea7559cc9a28881e8479cb896778f67f6beccac19685c522fb375e7d7",
  "presented_to_user": true,
  "source_ref": "DCL-DISPATCHER-DAEMON-RECOVERY-SLA-001",
  "transcript_captured": true
}
