[
  {
    "id": "C.1",
    "description": "Version updated",
    "status": "PASS",
    "detail": "expected=1.79.2, got=1.79.2"
  },
  {
    "id": "C.2",
    "description": "Tenant status unchanged",
    "status": "FAIL",
    "detail": "? vs active"
  },
  {
    "id": "C.3",
    "description": "Configuration state unchanged",
    "status": "FAIL",
    "detail": "active=None, configured=None"
  },
  {
    "id": "C.4",
    "description": "Conversation count not decreased",
    "status": "FAIL",
    "detail": "-1 vs 373 (growth OK)"
  },
  {
    "id": "C.5",
    "description": "Status breakdown unchanged",
    "status": "FAIL",
    "detail": "{}"
  },
  {
    "id": "C.6",
    "description": "KB article count unchanged",
    "status": "FAIL",
    "detail": "-1 vs 17"
  },
  {
    "id": "C.7",
    "description": "Team member count unchanged",
    "status": "FAIL",
    "detail": "0 vs 1"
  },
  {
    "id": "C.8",
    "description": "Team members unchanged",
    "status": "FAIL",
    "detail": ""
  },
  {
    "id": "C.9",
    "description": "Draft config unchanged",
    "status": "FAIL",
    "detail": "HTTP 429 vs 200"
  },
  {
    "id": "C.10",
    "description": "Active config unchanged",
    "status": "FAIL",
    "detail": "1 keys vs 7"
  },
  {
    "id": "C.11",
    "description": "Widget key still valid",
    "status": "FAIL",
    "detail": "HTTP 429"
  },
  {
    "id": "C.12",
    "description": "API key authenticates",
    "status": "FAIL",
    "detail": "HTTP 429"
  },
  {
    "id": "C.13",
    "description": "Regression tests",
    "status": "PASS",
    "detail": "SKIP \u2014 requires local pytest run"
  },
  {
    "id": "C.14",
    "description": "Superadmin API functional",
    "status": "FAIL",
    "detail": "HTTP 403, total=0"
  },
  {
    "id": "C.15",
    "description": "Public status API",
    "status": "PASS",
    "detail": "HTTP 200"
  },
  {
    "id": "C.16",
    "description": "Provider SPA served",
    "status": "PASS",
    "detail": "HTTP 200"
  },
  {
    "id": "C.17",
    "description": "Incidents endpoint",
    "status": "FAIL",
    "detail": "HTTP 403"
  },
  {
    "id": "C.18",
    "description": "Alert rules endpoint",
    "status": "FAIL",
    "detail": "HTTP 403"
  },
  {
    "id": "C.19",
    "description": "MFA endpoint",
    "status": "FAIL",
    "detail": "HTTP 403"
  },
  {
    "id": "C.20",
    "description": "Magic link request",
    "status": "FAIL",
    "detail": "HTTP 422"
  },
  {
    "id": "C.21",
    "description": "Analytics filtering",
    "status": "PASS",
    "detail": "HTTP 200"
  },
  {
    "id": "C.22",
    "description": "Archive endpoint",
    "status": "PASS",
    "detail": "HTTP 404"
  },
  {
    "id": "C.23",
    "description": "Support diagnostics",
    "status": "FAIL",
    "detail": "HTTP 403"
  },
  {
    "id": "C.24",
    "description": "Cost analytics",
    "status": "FAIL",
    "detail": "HTTP 403"
  },
  {
    "id": "C.25",
    "description": "Abuse detection",
    "status": "FAIL",
    "detail": "HTTP 403"
  },
  {
    "id": "C.26",
    "description": "Avatar upload",
    "status": "PASS",
    "detail": "SKIP \u2014 requires multipart file upload"
  },
  {
    "id": "C.27",
    "description": "Tier listing",
    "status": "PASS",
    "detail": "HTTP 200"
  },
  {
    "id": "C.28",
    "description": "Add-on listing",
    "status": "PASS",
    "detail": "HTTP 200, total=4"
  },
  {
    "id": "C.29",
    "description": "Memory stats",
    "status": "PASS",
    "detail": "HTTP 200"
  },
  {
    "id": "C.30",
    "description": "Config locking",
    "status": "PASS",
    "detail": "HTTP 503 (503 accepted: cold start)"
  },
  {
    "id": "C.31",
    "description": "FCR metric",
    "status": "PASS",
    "detail": "HTTP 200"
  },
  {
    "id": "C.32",
    "description": "Tier upgrade preview",
    "status": "PASS",
    "detail": "HTTP 400"
  },
  {
    "id": "C.33",
    "description": "Unit test count gate",
    "status": "PASS",
    "detail": "SKIP \u2014 requires local pytest"
  },
  {
    "id": "C.34",
    "description": "Evaluation framework loads",
    "status": "PASS",
    "detail": "SKIP \u2014 requires local Python"
  },
  {
    "id": "C.35",
    "description": "Critic rule integrity",
    "status": "PASS",
    "detail": "SKIP \u2014 requires local Python"
  }
]